{
  "trips": {
    "TRIP_LJ1E9Q": {
      "tripId": "TRIP_LJ1E9Q",
      "numTeams": 2,
      "playersPerTeam": 4,
      "numRounds": 3,
      "courses": [
        "True Blue",
        "True Blue",
        "True Blue"
      ],
      "scoringMethods": [
        "match",
        "match",
        "match"
      ],
      "teams": [
        {
          "name": "Team 1",
          "players": [
            {
              "name": "Player 1",
              "scores": [
                0,
                0,
                0
              ],
              "lineupOrder": [
                0,
                0,
                0
              ]
            },
            {
              "name": "Player 2",
              "scores": [
                0,
                0,
                0
              ],
              "lineupOrder": [
                1,
                1,
                1
              ]
            },
            {
              "name": "Player 3",
              "scores": [
                0,
                0,
                0
              ],
              "lineupOrder": [
                2,
                2,
                2
              ]
            },
            {
              "name": "Player 4",
              "scores": [
                0,
                0,
                0
              ],
              "lineupOrder": [
                3,
                3,
                3
              ]
            }
          ]
        },
        {
          "name": "Team 2",
          "players": [
            {
              "name": "Player 1",
              "scores": [
                0,
                0,
                0
              ],
              "lineupOrder": [
                0,
                0,
                0
              ]
            },
            {
              "name": "Player 2",
              "scores": [
                0,
                0,
                0
              ],
              "lineupOrder": [
                1,
                1,
                1
              ]
            },
            {
              "name": "Player 3",
              "scores": [
                0,
                0,
                0
              ],
              "lineupOrder": [
                2,
                2,
                2
              ]
            },
            {
              "name": "Player 4",
              "scores": [
                0,
                0,
                0
              ],
              "lineupOrder": [
                3,
                3,
                3
              ]
            }
          ]
        }
      ]
    },
    "TRIP_C3WPBU": {
      "tripId": "TRIP_C3WPBU",
      "numTeams": 2,
      "playersPerTeam": 4,
      "numRounds": 3,
      "courses": [
        "True Blue",
        "True Blue",
        "True Blue"
      ],
      "scoringMethods": [
        "match",
        "match",
        "match"
      ],
      "teams": [
        {
          "name": "Team 1",
          "players": [
            {
              "name": "Player 1",
              "scores": [
                0,
                0,
                0
              ],
              "lineupOrder": [
                0,
                0,
                0
              ]
            },
            {
              "name": "Player 2",
              "scores": [
                0,
                0,
                0
              ],
              "lineupOrder": [
                1,
                1,
                1
              ]
            },
            {
              "name": "Player 3",
              "scores": [
                0,
                0,
                0
              ],
              "lineupOrder": [
                2,
                2,
                2
              ]
            },
            {
              "name": "Player 4",
              "scores": [
                0,
                0,
                0
              ],
              "lineupOrder": [
                3,
                3,
                3
              ]
            }
          ]
        },
        {
          "name": "Team 2",
          "players": [
            {
              "name": "Player 1",
              "scores": [
                0,
                0,
                0
              ],
              "lineupOrder": [
                0,
                0,
                0
              ]
            },
            {
              "name": "Player 2",
              "scores": [
                0,
                0,
                0
              ],
              "lineupOrder": [
                1,
                1,
                1
              ]
            },
            {
              "name": "Player 3",
              "scores": [
                0,
                0,
                0
              ],
              "lineupOrder": [
                2,
                2,
                2
              ]
            },
            {
              "name": "Player 4",
              "scores": [
                0,
                0,
                0
              ],
              "lineupOrder": [
                3,
                3,
                3
              ]
            }
          ]
        }
      ]
    },
    "TRIP_OHB150": {
      "tripId": "TRIP_OHB150",
      "numTeams": 2,
      "playersPerTeam": 4,
      "numRounds": 3,
      "courses": [
        "True Blue",
        "True Blue",
        "True Blue"
      ],
      "scoringMethods": [
        "match",
        "match",
        "match"
      ],
      "teams": [
        {
          "name": "Team 1",
          "players": [
            {
              "name": "Player 1",
              "scores": [
                0,
                0,
                0
              ],
              "lineupOrder": [
                0,
                0,
                0
              ]
            },
            {
              "name": "Player 2",
              "scores": [
                0,
                0,
                0
              ],
              "lineupOrder": [
                1,
                1,
                1
              ]
            },
            {
              "name": "Player 3",
              "scores": [
                0,
                0,
                0
              ],
              "lineupOrder": [
                2,
                2,
                2
              ]
            },
            {
              "name": "Player 4",
              "scores": [
                0,
                0,
                0
              ],
              "lineupOrder": [
                3,
                3,
                3
              ]
            }
          ]
        },
        {
          "name": "Team 2",
          "players": [
            {
              "name": "Player 1",
              "scores": [
                0,
                0,
                0
              ],
              "lineupOrder": [
                0,
                0,
                0
              ]
            },
            {
              "name": "Player 2",
              "scores": [
                0,
                0,
                0
              ],
              "lineupOrder": [
                1,
                1,
                1
              ]
            },
            {
              "name": "Player 3",
              "scores": [
                0,
                0,
                0
              ],
              "lineupOrder": [
                2,
                2,
                2
              ]
            },
            {
              "name": "Player 4",
              "scores": [
                0,
                0,
                0
              ],
              "lineupOrder": [
                3,
                3,
                3
              ]
            }
          ]
        }
      ]
    },
    "TRIP_9O4N8V": {
      "tripId": "TRIP_9O4N8V",
      "numTeams": 2,
      "playersPerTeam": 4,
      "numRounds": 3,
      "courses": [
        "True Blue",
        "True Blue",
        "True Blue"
      ],
      "scoringMethods": [
        "match",
        "match",
        "match"
      ],
      "teams": [
        {
          "name": "Team 1",
          "players": [
            {
              "name": "Player 1",
              "scores": [
                0,
                0,
                0
              ],
              "lineupOrder": [
                0,
                0,
                0
              ]
            },
            {
              "name": "Player 2",
              "scores": [
                0,
                0,
                0
              ],
              "lineupOrder": [
                1,
                1,
                1
              ]
            },
            {
              "name": "Player 3",
              "scores": [
                0,
                0,
                0
              ],
              "lineupOrder": [
                2,
                2,
                2
              ]
            },
            {
              "name": "Player 4",
              "scores": [
                0,
                0,
                0
              ],
              "lineupOrder": [
                3,
                3,
                3
              ]
            }
          ]
        },
        {
          "name": "Team 2",
          "players": [
            {
              "name": "Player 1",
              "scores": [
                0,
                0,
                0
              ],
              "lineupOrder": [
                0,
                0,
                0
              ]
            },
            {
              "name": "Player 2",
              "scores": [
                0,
                0,
                0
              ],
              "lineupOrder": [
                1,
                1,
                1
              ]
            },
            {
              "name": "Player 3",
              "scores": [
                0,
                0,
                0
              ],
              "lineupOrder": [
                2,
                2,
                2
              ]
            },
            {
              "name": "Player 4",
              "scores": [
                0,
                0,
                0
              ],
              "lineupOrder": [
                3,
                3,
                3
              ]
            }
          ]
        }
      ]
    },
    "TRIP_CUCVVK": {
      "tripId": "TRIP_CUCVVK",
      "numTeams": 2,
      "playersPerTeam": 4,
      "numRounds": 3,
      "courses": [
        "True Blue",
        "True Blue",
        "True Blue"
      ],
      "scoringMethods": [
        "match",
        "match",
        "match"
      ],
      "teams": [
        {
          "name": "Team 1",
          "players": [
            {
              "id": 1,
              "name": "Player 1",
              "scores": [
                0,
                0,
                0
              ],
              "lineupOrder": [
                0,
                0,
                0
              ]
            },
            {
              "id": 2,
              "name": "Player 2",
              "scores": [
                0,
                0,
                0
              ],
              "lineupOrder": [
                1,
                1,
                1
              ]
            },
            {
              "id": 3,
              "name": "Player 3",
              "scores": [
                0,
                0,
                0
              ],
              "lineupOrder": [
                2,
                2,
                2
              ]
            },
            {
              "id": 4,
              "name": "Player 4",
              "scores": [
                0,
                0,
                0
              ],
              "lineupOrder": [
                3,
                3,
                3
              ]
            }
          ]
        },
        {
          "name": "Team 2",
          "players": [
            {
              "id": 1,
              "name": "Player 1",
              "scores": [
                0,
                0,
                0
              ],
              "lineupOrder": [
                0,
                0,
                0
              ]
            },
            {
              "id": 2,
              "name": "Player 2",
              "scores": [
                0,
                0,
                0
              ],
              "lineupOrder": [
                1,
                1,
                1
              ]
            },
            {
              "id": 3,
              "name": "Player 3",
              "scores": [
                0,
                0,
                0
              ],
              "lineupOrder": [
                2,
                2,
                2
              ]
            },
            {
              "id": 4,
              "name": "Player 4",
              "scores": [
                0,
                0,
                0
              ],
              "lineupOrder": [
                3,
                3,
                3
              ]
            }
          ]
        }
      ]
    },
    "TRIP_6R79HT": {
      "tripId": "TRIP_6R79HT",
      "numTeams": 2,
      "playersPerTeam": 4,
      "numRounds": 3,
      "courses": [
        "True Blue",
        "True Blue",
        "True Blue"
      ],
      "scoringMethods": [
        "match",
        "match",
        "match"
      ],
      "teams": [
        {
          "name": "Team 1",
          "players": [
            {
              "id": 1,
              "name": "Player 1",
              "scores": [
                0,
                0,
                0
              ],
              "lineupOrder": [
                0,
                0,
                0
              ]
            },
            {
              "id": 2,
              "name": "Player 2",
              "scores": [
                0,
                0,
                0
              ],
              "lineupOrder": [
                1,
                1,
                1
              ]
            },
            {
              "id": 3,
              "name": "Player 3",
              "scores": [
                0,
                0,
                0
              ],
              "lineupOrder": [
                2,
                2,
                2
              ]
            },
            {
              "id": 4,
              "name": "Player 4",
              "scores": [
                0,
                0,
                0
              ],
              "lineupOrder": [
                3,
                3,
                3
              ]
            }
          ]
        },
        {
          "name": "Team 2",
          "players": [
            {
              "id": 1,
              "name": "Player 1",
              "scores": [
                0,
                0,
                0
              ],
              "lineupOrder": [
                0,
                0,
                0
              ]
            },
            {
              "id": 2,
              "name": "Player 2",
              "scores": [
                0,
                0,
                0
              ],
              "lineupOrder": [
                1,
                1,
                1
              ]
            },
            {
              "id": 3,
              "name": "Player 3",
              "scores": [
                0,
                0,
                0
              ],
              "lineupOrder": [
                2,
                2,
                2
              ]
            },
            {
              "id": 4,
              "name": "Player 4",
              "scores": [
                0,
                0,
                0
              ],
              "lineupOrder": [
                3,
                3,
                3
              ]
            }
          ]
        }
      ]
    },
    "TRIP_30GFZL": {
      "tripId": "TRIP_30GFZL",
      "numTeams": 2,
      "playersPerTeam": 4,
      "numRounds": 2,
      "courses": [
        "True Blue",
        "True Blue"
      ],
      "scoringMethods": [
        "match",
        "match"
      ],
      "teams": [
        {
          "name": "Team 1",
          "players": [
            {
              "id": 1,
              "name": "Player 1",
              "scores": [
                0,
                0
              ],
              "lineupOrder": [
                0,
                0
              ]
            },
            {
              "id": 2,
              "name": "Player 2",
              "scores": [
                0,
                0
              ],
              "lineupOrder": [
                0,
                0
              ]
            },
            {
              "id": 3,
              "name": "Player 3",
              "scores": [
                0,
                0
              ],
              "lineupOrder": [
                0,
                0
              ]
            },
            {
              "id": 4,
              "name": "Player 4",
              "scores": [
                0,
                0
              ],
              "lineupOrder": [
                0,
                0
              ]
            }
          ]
        },
        {
          "name": "Team 2",
          "players": [
            {
              "id": 1,
              "name": "Player 1",
              "scores": [
                0,
                0
              ],
              "lineupOrder": [
                0,
                0
              ]
            },
            {
              "id": 2,
              "name": "Player 2",
              "scores": [
                0,
                0
              ],
              "lineupOrder": [
                0,
                0
              ]
            },
            {
              "id": 3,
              "name": "Player 3",
              "scores": [
                0,
                0
              ],
              "lineupOrder": [
                0,
                0
              ]
            },
            {
              "id": 4,
              "name": "Player 4",
              "scores": [
                0,
                0
              ],
              "lineupOrder": [
                0,
                0
              ]
            }
          ]
        }
      ]
    },
    "TRIP_N13LNG": {
      "tripId": "TRIP_N13LNG",
      "numTeams": 2,
      "playersPerTeam": 4,
      "numRounds": 3,
      "scoringMethods": [
        "match",
        "match",
        "match"
      ],
      "courses": [
        "True Blue",
        "True Blue",
        "True Blue"
      ],
      "teams": [
        {
          "name": "Team 1",
          "players": [
            {
              "name": "Player 1",
              "scores": [
                0,
                0,
                0
              ],
              "lineupOrder": [
                0,
                0,
                0
              ]
            },
            {
              "name": "Player 2",
              "scores": [
                0,
                0,
                0
              ],
              "lineupOrder": [
                1,
                1,
                1
              ]
            },
            {
              "name": "Player 3",
              "scores": [
                0,
                0,
                0
              ],
              "lineupOrder": [
                2,
                2,
                2
              ]
            },
            {
              "name": "Player 4",
              "scores": [
                0,
                0,
                0
              ],
              "lineupOrder": [
                3,
                3,
                3
              ]
            }
          ]
        },
        {
          "name": "Team 2",
          "players": [
            {
              "name": "Player 1",
              "scores": [
                0,
                0,
                0
              ],
              "lineupOrder": [
                0,
                0,
                0
              ]
            },
            {
              "name": "Player 2",
              "scores": [
                0,
                0,
                0
              ],
              "lineupOrder": [
                1,
                1,
                1
              ]
            },
            {
              "name": "Player 3",
              "scores": [
                0,
                0,
                0
              ],
              "lineupOrder": [
                2,
                2,
                2
              ]
            },
            {
              "name": "Player 4",
              "scores": [
                0,
                0,
                0
              ],
              "lineupOrder": [
                3,
                3,
                3
              ]
            }
          ]
        }
      ]
    },
    "TRIP_ATXWKN": {
      "tripId": "TRIP_ATXWKN",
      "numTeams": 2,
      "playersPerTeam": 4,
      "numRounds": 1,
      "scoringMethods": [
        "match",
        "match",
        "match"
      ],
      "courses": [
        "True Blue",
        "True Blue",
        "True Blue"
      ],
      "teams": [
        {
          "name": "Team 1",
          "players": [
            {
              "name": "Player 1",
              "scores": [
                0,
                0,
                0
              ],
              "lineupOrder": [
                0,
                0,
                0
              ]
            },
            {
              "name": "Player 2",
              "scores": [
                0,
                0,
                0
              ],
              "lineupOrder": [
                1,
                1,
                1
              ]
            },
            {
              "name": "Player 3",
              "scores": [
                0,
                0,
                0
              ],
              "lineupOrder": [
                2,
                2,
                2
              ]
            },
            {
              "name": "Player 4",
              "scores": [
                0,
                0,
                0
              ],
              "lineupOrder": [
                3,
                3,
                3
              ]
            }
          ]
        },
        {
          "name": "Team 2",
          "players": [
            {
              "name": "Player 1",
              "scores": [
                0,
                0,
                0
              ],
              "lineupOrder": [
                0,
                0,
                0
              ]
            },
            {
              "name": "Player 2",
              "scores": [
                0,
                0,
                0
              ],
              "lineupOrder": [
                1,
                1,
                1
              ]
            },
            {
              "name": "Player 3",
              "scores": [
                0,
                0,
                0
              ],
              "lineupOrder": [
                2,
                2,
                2
              ]
            },
            {
              "name": "Player 4",
              "scores": [
                0,
                0,
                0
              ],
              "lineupOrder": [
                3,
                3,
                3
              ]
            }
          ]
        }
      ]
    },
    "TRIP_SQ1ESC": {
      "tripId": "TRIP_SQ1ESC",
      "numTeams": 2,
      "playersPerTeam": 4,
      "numRounds": 2,
      "scoringMethods": [
        "match",
        "match"
      ],
      "courses": [
        "True Blue",
        "True Blue"
      ],
      "teams": []
    }
  }
}